{
  "name": "Arnold Ruijter IT",
  "documentation": "",
  "platformIntro": "",
  "platformConfig": {
    "defaultLang": "en",
    "processes": {},
    "views": {}
  },
  "elements": [],
  "relationships": [],
  "processes": [],
  "views": [],
  "snapshots": [],
  "elementPositions": {},
  "businessSystems": {
    "apps": [
      {
        "id": "bs-mo72515d-gmfy4",
        "name": "SAP S/4",
        "description": "ERP for Finance, Order2Cash, and central repository",
        "x": 20,
        "y": 40
      },
      {
        "id": "bs-mo725dyl-60c98",
        "name": "Boomi",
        "description": "Middleware for routing and mapping messages, including API Management",
        "x": 210,
        "y": 40
      },
      {
        "id": "bs-mo725zj5-xwmf9",
        "name": "SalesForce",
        "description": "eCom platform for B2C",
        "x": 400,
        "y": 40
      },
      {
        "id": "bs-mo727hdv-rc2in",
        "name": "New Black",
        "description": "POS (Point Of Sales) platform - central with connections to all till systems in stores",
        "x": 590,
        "y": 40
      },
      {
        "id": "bs-mo7281l2-v0twv",
        "name": "PIM",
        "description": "Product Information Management - containing user-friendly product information and media",
        "x": 780,
        "y": 40
      },
      {
        "id": "bs-mo72918a-q05hb",
        "name": "PLM",
        "description": "Product Lifecycle Management - for building products and having manufacturers upload their details + tech-packs",
        "x": 970,
        "y": 40
      },
      {
        "id": "bs-mo729p7b-sk3gw",
        "name": "SAP WHM",
        "description": "Warehouse Management system",
        "x": 1160,
        "y": 40
      }
    ],
    "departments": [],
    "roles": [],
    "roleRelations": [],
    "appRelations": [],
    "orgName": "Arnold Ruijter IT",
    "bsProcesses": []
  }
}